{
  "$schema": "urn:watchtower:schema:artifacts:plan:initiative-event-stream:v1",
  "event_id": "event.hosted_pack_parity_scaffold_and_plan_runtime_flattening.0015_completed",
  "initiative_id": "initiative.hosted_pack_parity_scaffold_and_plan_runtime_flattening",
  "sequence": 15,
  "event_type": "completed",
  "actor_id": "actor.repository_maintainer",
  "recorded_at": "2026-03-21T03:56:17Z",
  "summary": "The initiative package reached terminal closeout as completed.",
  "payload": {},
  "trace_id": "trace.hosted_pack_parity_scaffold_and_plan_runtime_flattening"
}
