{
  "$schema": "urn:watchtower:schema:artifacts:plan:initiative-event-stream:v1",
  "event_id": "event.ledger_retirement_contract_change.0009_authored_inputs_confirmed",
  "initiative_id": "initiative.ledger_retirement_contract_change",
  "sequence": 9,
  "event_type": "authored_inputs_confirmed",
  "actor_id": "actor.repository_maintainer",
  "recorded_at": "2026-03-21T21:56:28Z",
  "summary": "An authorized maintainer confirmed the authored intake documents into machine state.",
  "payload": {},
  "trace_id": "trace.ledger_retirement_contract_change"
}
