{
  "$schema": "urn:watchtower:schema:artifacts:plan:initiative-event-stream:v1",
  "event_id": "event.core_removable_plan_reference_cleanup.0012_ready_for_execution_approved",
  "initiative_id": "initiative.core_removable_plan_reference_cleanup",
  "sequence": 12,
  "event_type": "ready_for_execution_approved",
  "actor_id": "actor.repository_maintainer",
  "recorded_at": "2026-03-22T23:14:06Z",
  "summary": "An authorized maintainer approved the initiative package for execution.",
  "payload": {},
  "trace_id": "trace.core_removable_plan_reference_cleanup"
}
