{
  "$schema": "urn:watchtower:schema:artifacts:plan:initiative-event-stream:v1",
  "event_id": "event.plan_project_context_runtime_standardization.0013_completed",
  "initiative_id": "initiative.plan_project_context_runtime_standardization",
  "trace_id": "trace.plan_project_context_runtime_standardization",
  "sequence": 13,
  "event_type": "completed",
  "actor_id": "actor.repository_maintainer",
  "recorded_at": "2026-03-17T18:58:00Z",
  "summary": "The initiative package reached terminal closeout as completed.",
  "payload": {}
}
