{
  "$schema": "urn:watchtower:schema:artifacts:plan:task-state:v1",
  "task_id": "task.plan_workflow_execution_harness_foundation.reconcile_requirements_and_package_docs",
  "slug": "reconcile_requirements_and_package_docs",
  "initiative_id": "initiative.plan_workflow_execution_harness_foundation",
  "title": "Reconcile requirements and package docs",
  "summary": "Update requirements.md and package documentation to mark workflow execution current at the reusable-core boundary.",
  "status": "active",
  "task_kind": "feature",
  "priority": "high",
  "owner": "repository_maintainer",
  "created_at": "2026-03-18T00:47:00Z",
  "updated_at": "2026-03-18T00:55:00Z",
  "dependency_task_ids": [],
  "blocker_task_ids": [],
  "related_ids": [],
  "task_status": "completed"
}
